unet3d/__init__.py
unet3d/linknet3d.py
unet3d/unet3d.py
unet3d-0.1.0.dist-info/METADATA
unet3d-0.1.0.dist-info/WHEEL
unet3d-0.1.0.dist-info/RECORD
